pdf/Pdf.py
pdf/__init__.py
pdf/convert_pdf_to_html.py
pdf/convert_pdf_to_xml.py
pdf/extract_text.py
pdf/exceptions/__init__.py
pdf/string/__init__.py
pdf/string/ends_with_punctuation.py
pdf/string/get_alphabetic.py
pdf/string/get_alphabetic_ratio.py
pdf/string/get_numeric_ratio.py
pdf/string/get_words.py
pdf/string/is_capitalized.py
pdf/string/is_short_text.py
pdf/string/strip_non_alphanumeric_from_beginning.py
pdf/tag/__init__.py
pdf/tag/get_border.py
pdf/tag/get_children.py
pdf/tag/get_font_size.py
pdf/tag/get_raw_text.py
pdf/tag/get_text.py
pdf/tag/is_break.py
pdf/tag/is_tag_title.py
pdf/tag/previous_tag_might_be_title.py
pdf-2020.11.12.dist-info/METADATA
pdf-2020.11.12.dist-info/WHEEL
pdf-2020.11.12.dist-info/top_level.txt
pdf-2020.11.12.dist-info/zip-safe
pdf-2020.11.12.dist-info/RECORD
